metric_collector/__init__.py
metric_collector-0.2.1.dist-info/LICENSE
metric_collector-0.2.1.dist-info/WHEEL
metric_collector-0.2.1.dist-info/METADATA
metric_collector-0.2.1.dist-info/RECORD
